wsi_genie_training_tasks/__init__.py
wsi_genie_training_tasks/config.py
wsi_genie_training_tasks/pooler.py
wsi_genie_training_tasks/tasks.py
wsi_genie_training_tasks/preprocessing/__init__.py
wsi_genie_training_tasks/preprocessing/extractor.py
wsi_genie_training_tasks/preprocessing/patcher.py
wsi_genie_training_tasks/preprocessing/wsi_annotations.py
wsi_genie_training_tasks/preprocessing/wsi_core/__init__.py
wsi_genie_training_tasks/preprocessing/wsi_core/batch_process_utils.py
wsi_genie_training_tasks/preprocessing/wsi_core/util_classes.py
wsi_genie_training_tasks/preprocessing/wsi_core/wsi_object.py
wsi_genie_training_tasks/preprocessing/wsi_core/wsi_utils.py
wsi_genie_training_tasks-0.0.0.dist-info/METADATA
wsi_genie_training_tasks-0.0.0.dist-info/WHEEL
wsi_genie_training_tasks-0.0.0.dist-info/entry_points.txt
wsi_genie_training_tasks-0.0.0.dist-info/top_level.txt
wsi_genie_training_tasks-0.0.0.dist-info/RECORD
