Metadata-Version: 2.1
Name: wsi_genie_training_tasks
Version: 0.0.0
Summary: Plugin to register Training and Testing tasks with girder worker
Author: Parth
Author-email: pas353@pitt.edu
License: Apache Software License 2.0
Classifier: Development Status :: 2 - Pre-Alpha
Classifier: License :: OSI Approved :: Apache Software License
Classifier: Topic :: Scientific/Engineering
Classifier: Intended Audience :: Science/Research
Classifier: Natural Language :: English
Classifier: Programming Language :: Python
Requires-Dist: girder-worker
Requires-Dist: girder-worker-utils
Provides-Extra: girder
Provides-Extra: worker
